a1_loggermanager/__init__.py
a1_loggermanager/handlers/my_file_handler.py
a1_loggermanager/handlers/my_rotating_file_handler.py
a1_loggermanager/handlers/my_stream_handler.py
a1_loggermanager/handlers/my_timed_rotating_file_handler.py
a1_loggermanager/logger_manager.py
a1_loggermanager/my_formatter.py
a1_loggermanager/my_handler.py
a1_loggermanager/my_logger.py
a1_loggermanager-0.1.4.dist-info/METADATA
a1_loggermanager-0.1.4.dist-info/WHEEL
a1_loggermanager-0.1.4.dist-info/RECORD
