Metadata-Version: 2.1
Name: a1_loggermanager
Version: 0.1.4
Summary: 
Author: a1p
Author-email: mike@a1publishing.com
Requires-Python: >=3.13,<4.0
Classifier: Programming Language :: Python :: 3
Classifier: Programming Language :: Python :: 3.13
